MANIFEST.in
README.md
setup.py
ayd/__init__.py
ayd/generate_flow.py
ayd/main.py
ayd/migrate.py
ayd.egg-info/PKG-INFO
ayd.egg-info/SOURCES.txt
ayd.egg-info/dependency_links.txt
ayd.egg-info/entry_points.txt
ayd.egg-info/pbr.json
ayd.egg-info/requires.txt
ayd.egg-info/top_level.txt