Metadata-Version: 1.1
Name: ayd
Version: 0.0.5
Summary: generate Azkaban Flow
Home-page: https://github.com/wyukawa/ayd
Author: wyukawa
Author-email: wyukawa@gmail.com
License: MIT
Platform: UNKNOWN
Classifier: Development Status :: 3 - Alpha
Classifier: Intended Audience :: Developers
Classifier: License :: OSI Approved :: MIT License
Classifier: Programming Language :: Python
Classifier: Programming Language :: Python :: 2.7
Classifier: Environment :: Console
